benchmarkfcns.libs/libstdc++-a9383cce.so.6.0.28
benchmarkfcns.libs/libgcc_s-a04fdf82.so.1
benchmarkfcns-3.1.0.dist-info/METADATA
benchmarkfcns-3.1.0.dist-info/RECORD
benchmarkfcns-3.1.0.dist-info/WHEEL
benchmarkfcns-3.1.0.dist-info/licenses/LICENSE
benchmarkfcns/__init__.py
benchmarkfcns/_core.cpython-39-x86_64-linux-gnu.so
benchmarkfcns/plotting.py
benchmarkfcns/multifidelity/__init__.py
