Metadata-Version: 2.1
Name: benchmarkfcns
Version: 3.1.0
Summary: A high-performant C++ implementation of benchmark functions for mathematical optimization algorithms.
Author-Email: Mazhar Ansari Ardeh <mazhar.ansari.ardeh@gmail.com>
Classifier: Development Status :: 4 - Beta
Classifier: License :: OSI Approved :: MIT License
Classifier: Programming Language :: Python :: 3 :: Only
Classifier: Programming Language :: Python :: 3.9
Classifier: Programming Language :: Python :: 3.10
Classifier: Programming Language :: Python :: 3.11
Classifier: Programming Language :: Python :: 3.12
Requires-Python: >=3.9
Requires-Dist: numpy<2,>=1.26
Requires-Dist: pytest; extra == "test"
Provides-Extra: test
